dsw/models/__init__.py
dsw/models/build_info.py
dsw/models/common.py
dsw/models/document_template/__init__.py
dsw/models/document_template/metadata.py
dsw/models/knowledge_model/__init__.py
dsw/models/knowledge_model/common.py
dsw/models/knowledge_model/events.py
dsw/models/knowledge_model/flat.py
dsw/models/knowledge_model/package.py
dsw/models/knowledge_model/tree.py
dsw_models-4.26.1.dist-info/licenses/LICENSE
dsw_models-4.26.1.dist-info/METADATA
dsw_models-4.26.1.dist-info/WHEEL
dsw_models-4.26.1.dist-info/top_level.txt
dsw_models-4.26.1.dist-info/RECORD
