Metadata-Version: 2.4
Name: dsw-models
Version: 4.26.1
Summary: Library with DSW models and basic IO operations
Author-email: Marek Suchánek <marek.suchanek@ds-wizard.org>
License: Apache License 2.0
Project-URL: Homepage, https://ds-wizard.org
Project-URL: Repository, https://github.com/ds-wizard/engine-tools
Project-URL: Documentation, https://guide.ds-wizard.org
Keywords: dsw,config,yaml,parser
Classifier: Development Status :: 4 - Beta
Classifier: License :: OSI Approved :: Apache Software License
Classifier: Programming Language :: Python
Classifier: Programming Language :: Python :: 3.12
Classifier: Programming Language :: Python :: 3.13
Classifier: Programming Language :: Python :: 3.14
Classifier: Topic :: Text Processing
Classifier: Topic :: Utilities
Requires-Python: <4,>=3.12
License-File: LICENSE
Requires-Dist: pydantic
Dynamic: license-file
